libfuzzer/__init__.py
libfuzzer/libfuzzer.py
libfuzzer/include/LibFuzzer.h
libfuzzer/lib/libfuzzer.so
libfuzzer-0.0.2.dist-info/RECORD
libfuzzer-0.0.2.dist-info/top_level.txt
libfuzzer-0.0.2.dist-info/METADATA
libfuzzer-0.0.2.dist-info/WHEEL
