Metadata-Version: 2.1
Name: libfuzzer
Version: 0.0.2
Summary: libfuzzer
Home-page: https://github.com/wtdcode/libfuzzer
Author: Lazymio
Author-email: mio@lazym.io
License: UNKNOWN
Platform: UNKNOWN
Classifier: Programming Language :: Python :: 3
Requires: ctypes
Provides: libfuzzer
